rustflight-0.1.1.dist-info/METADATA
rustflight-0.1.1.dist-info/WHEEL
rustflight/__init__.py
rustflight/rustflight.cpython-39-x86_64-linux-gnu.so
rustflight-0.1.1.dist-info/RECORD
