Metadata-Version: 2.4
Name: rustflight
Version: 0.1.1
